refgetter/__init__.py
tests/__init__.py
tests/cli_test.py
refgetter-0.0.1.dist-info/LICENSE
refgetter-0.0.1.dist-info/METADATA
refgetter-0.0.1.dist-info/WHEEL
refgetter-0.0.1.dist-info/entry_points.txt
refgetter-0.0.1.dist-info/top_level.txt
refgetter-0.0.1.dist-info/RECORD
