Metadata-Version: 2.1
Name: refgetter
Version: 0.0.1
Summary: A refget package for retrieving data about genomic references.
Home-page: https://github.com/zmunro/refgetter
Author: Zach Munro
Author-email: zacharymunro2@gmail.com
License: UNKNOWN
Platform: UNKNOWN
Classifier: Programming Language :: Python :: 3
Classifier: License :: OSI Approved :: MIT License
Classifier: Operating System :: OS Independent
Requires-Dist: fire
Requires-Dist: requests
Requires-Dist: backoff
